gimp_labeling_converter/__init__.py
gimp_labeling_converter/__main__.py
gimp_labeling_converter/class_map.py
gimp_labeling_converter/coco.py
gimp_labeling_converter/dataset.py
gimp_labeling_converter/gimp.py
gimp_labeling_converter/mask.py
gimp_labeling_converter-2.0.0.dist-info/LICENSE
gimp_labeling_converter-2.0.0.dist-info/METADATA
gimp_labeling_converter-2.0.0.dist-info/WHEEL
gimp_labeling_converter-2.0.0.dist-info/entry_points.txt
gimp_labeling_converter-2.0.0.dist-info/top_level.txt
gimp_labeling_converter-2.0.0.dist-info/RECORD
