Metadata-Version: 2.1
Name: gimp-labeling-converter
Version: 2.0.0
Summary: it provides a CLI tool that converts XCF file to a new format suitable for labeling. The tool also make the users able to add their own handlers for addling support to other types of outputs.
Home-page: https://github.com/parham/gimp-labeling-converter
Author: Parham Nooralishahi
Author-email: parham.nooralishahi@gmail.com
License: BSD
Keywords: gimp data_labeling segmentation
Platform: UNKNOWN
Classifier: Programming Language :: Python :: 3
Classifier: License :: OSI Approved :: BSD License
Classifier: Operating System :: OS Independent
Classifier: Programming Language :: Python
Classifier: Topic :: Utilities
Classifier: Topic :: Software Development
Requires-Python: >=3.7
License-File: LICENSE
Requires-Dist: gimpformats
Requires-Dist: Pillow
Requires-Dist: scikit-image
Requires-Dist: glob2
Requires-Dist: torch
Requires-Dist: torchvision
